Workbook

Sheet Сводка
A1: OmniaCRM — функциональные сценарии (use cases) по ТЗ
A2: Без технологического стека: только то, что система должна делать. Источник — docs/tz.md; ID требований — ТР-x.y, открытые вопросы — ОВ-x.
A4: Область | B4: Всего | C4: Утверждено | D4: На согласовании | E4: Не определено
A5: Тенанты | B5: =COUNTA('Тенанты'!A:A)-1 | C5: =COUNTIF('Тенанты'!G:G,"Утверждено") | D5: =COUNTIF('Тенанты'!G:G,"На согласовании") | E5: =COUNTIF('Тенанты'!G:G,"Не определено")
A6: Клиенты | B6: =COUNTA('Клиенты'!A:A)-1 | C6: =COUNTIF('Клиенты'!G:G,"Утверждено") | D6: =COUNTIF('Клиенты'!G:G,"На согласовании") | E6: =COUNTIF('Клиенты'!G:G,"Не определено")
A7: Обращения | B7: =COUNTA('Обращения'!A:A)-1 | C7: =COUNTIF('Обращения'!G:G,"Утверждено") | D7: =COUNTIF('Обращения'!G:G,"На согласовании") | E7: =COUNTIF('Обращения'!G:G,"Не определено")
A8: Каталог | B8: =COUNTA('Каталог'!A:A)-1 | C8: =COUNTIF('Каталог'!G:G,"Утверждено") | D8: =COUNTIF('Каталог'!G:G,"На согласовании") | E8: =COUNTIF('Каталог'!G:G,"Не определено")
A9: Платежи | B9: =COUNTA('Платежи'!A:A)-1 | C9: =COUNTIF('Платежи'!G:G,"Утверждено") | D9: =COUNTIF('Платежи'!G:G,"На согласовании") | E9: =COUNTIF('Платежи'!G:G,"Не определено")
A10: Уведомления | B10: =COUNTA('Уведомления'!A:A)-1 | C10: =COUNTIF('Уведомления'!G:G,"Утверждено") | D10: =COUNTIF('Уведомления'!G:G,"На согласовании") | E10: =COUNTIF('Уведомления'!G:G,"Не определено")
A11: Интерфейс владельца | B11: =COUNTA('Интерфейс владельца'!A:A)-1 | C11: =COUNTIF('Интерфейс владельца'!G:G,"Утверждено") | D11: =COUNTIF('Интерфейс владельца'!G:G,"На согласовании") | E11: =COUNTIF('Интерфейс владельца'!G:G,"Не определено")
A12: Каналы | B12: =COUNTA('Каналы'!A:A)-1 | C12: =COUNTIF('Каналы'!G:G,"Утверждено") | D12: =COUNTIF('Каналы'!G:G,"На согласовании") | E12: =COUNTIF('Каналы'!G:G,"Не определено")
A13: Эксплуатация | B13: =COUNTA('Эксплуатация'!A:A)-1 | C13: =COUNTIF('Эксплуатация'!G:G,"Утверждено") | D13: =COUNTIF('Эксплуатация'!G:G,"На согласовании") | E13: =COUNTIF('Эксплуатация'!G:G,"Не определено")
A14: Итого | B14: =SUM(B5:B13) | C14: =SUM(C5:C13) | D14: =SUM(D5:D13) | E14: =SUM(E5:E13)
A16: Статусы
A17: Утверждено | B17: Решено командой — функцию реализуем.
A18: На согласовании | B18: Предложение, командой не подтверждено — не закладывать как решённое.
A19: Не определено | B19: Ответа нет — нужен вопрос команде (ОВ-x в ТЗ).
A21: Столбец «Статус в ТЗ» на листах областей — выпадающий список; сводка пересчитывается автоматически.

Sheet Тенанты
A1: ID | B1: Use case | C1: Актор | D1: Что делает система | E1: Результат | F1: Требования ТЗ | G1: Статус в ТЗ | H1: Открытые вопросы и примечания
A2: TEN-01 | B2: Подключить новый бизнес | C2: Команда платформы | D2: Заводит в системе новый бизнес как отдельный тенант, не меняя схему данных и архитектуру. | E2: Бизнес может принимать обращения через свои каналы. | F2: ТР-5.1; цели п. 3.2 | G2: Утверждено | H2: Делают разработчики при внедрении (ТР-8.8).
A3: TEN-02 | B3: Изолировать данные бизнесов | C3: Система (автоматически) | D3: Каждая операция выполняется в контексте одного тенанта. Данные разных бизнесов не смешиваются и не видны друг другу. | E3: Бизнес видит только свои данные. | F3: ТР-5.1; цели п. 3.2 | G3: Утверждено
A4: TEN-03 | B4: Настроить типы дел бизнеса | C4: Команда платформы | D4: Задаёт для бизнеса типы дел (запись, заявка, заказ, бронирование) и набор полей с правилами проверки для каждого типа. | E4: Обращения бизнеса принимаются по его собственной схеме полей. | F4: ТР-5.2; ТР-6.1 | G4: Утверждено | H4: Делают разработчики при внедрении (ТР-8.8).
A5: TEN-04 | B5: Вести профиль компании | C5: Команда платформы | D5: Хранит и изменяет данные бизнеса: название, адрес, контакты, логотип, режим работы. | E5: Актуальные данные бизнеса доступны его каналам. | F5: ТР-6.1; ТР-8.8 | G5: Утверждено | H5: Вносят разработчики при внедрении (ОВ-4 закрыт).
A6: TEN-05 | B6: Прогнать эталонный сценарий на Tenant Zero | C6: Команда платформы | D6: Заводит тестовый бизнес с вымышленными данными и прогоняет полный маршрут: обращение → оплата (тестовый режим) → уведомление → обращение в интерфейсе владельца. | E6: Маршрут проверен до подключения первого реального заказчика. | F6: ТР-16.1 | G6: На согласовании | H6: Issue #7. Минимум две структурно разные вертикали (ТР-4.3).

Sheet Клиенты
A1: ID | B1: Use case | C1: Актор | D1: Что делает система | E1: Результат | F1: Требования ТЗ | G1: Статус в ТЗ | H1: Открытые вопросы и примечания
A2: CLI-01 | B2: Зарегистрировать клиента при обращении | C2: Клиентская система | D2: При первом обращении создаёт карточку клиента с контактами. При повторном находит существующую и не создаёт дубль. | E2: У бизнеса есть единая карточка клиента. | F2: ТР-6.1; ТР-8.2 | G2: Утверждено | H2: Как опознаётся повторный клиент (телефон, email, Telegram), в ТЗ не описано.
A3: CLI-02 | B3: Просмотреть историю обращений клиента | C3: Бизнес | D3: Показывает все обращения клиента в рамках бизнеса и их состояния. | E3: Бизнес видит историю работы с клиентом. | F3: ТР-6.1 | G3: Утверждено | H3: В интерфейсе владельца.
A4: CLI-03 | B4: Импортировать клиентов и историю обращений | C4: Команда платформы | D4: Разово переносит клиентов и их прошлые обращения из базы данных или CSV-файлов существующего сайта. | E4: История бизнеса доступна в системе с первого дня. | F4: ТР-8.1 | G4: Утверждено | H4: Разовая процедура, не постоянная интеграция. Доступ к данным — ОВ-8.

Sheet Обращения
A1: ID | B1: Use case | C1: Актор | D1: Что делает система | E1: Результат | F1: Требования ТЗ | G1: Статус в ТЗ | H1: Открытые вопросы и примечания
A2: CASE-01 | B2: Создать обращение | C2: Клиент бизнеса | D2: Принимает обращение клиента с сайта или из Telegram-бота: запись на время, заявку, заказ или бронирование. Без контакта клиента обращение не принимается. | E2: Обращение зарегистрировано, клиент и бизнес уведомлены. | F2: ТР-4.1; ТР-6.1; ТР-8.5; ТР-8.6 | G2: Утверждено | H2: Обмен односторонний: статус клиенту через сайт не отдаётся.
A3: CASE-02 | B3: Исключить дубли при повторной отправке | C3: Система (автоматически) | D3: Если канал повторно отправил то же обращение (сбой сети, двойное нажатие), возвращает уже созданное, а не заводит новое. | E3: Одно действие клиента — одно обращение. | F3: ТР-5.4; ТР-14.3 | G3: Утверждено
A4: CASE-03 | B4: Проверить данные обращения | C4: Система (автоматически) | D4: Проверяет поля обращения по схеме его типа. Некорректное обращение отклоняет с понятной причиной. | E4: В системе только корректные обращения. | F4: ТР-5.2 | G4: Утверждено
A5: CASE-04 | B5: Изменить статус обращения | C5: Бизнес | D5: Переводит обращение в следующее состояние (например, «принято» → «выполнено») по допустимым переходам. | E5: Статус актуален, клиент уведомлён. | F5: ТР-6.1 | G5: Утверждено | H5: Набор статусов на старте может быть фиксированным, но должен дёшево меняться. Кто меняет статус — прямо не описано.
A6: CASE-05 | B6: Просмотреть обращения бизнеса | C6: Бизнес | D6: Показывает бизнесу поступившие обращения и их состояния. | E6: Бизнес видит поток обращений. | F6: ТР-4.4; ТР-12.2 | G6: Утверждено | H6: См. лист «Интерфейс владельца».

Sheet Каталог
A1: ID | B1: Use case | C1: Актор | D1: Что делает система | E1: Результат | F1: Требования ТЗ | G1: Статус в ТЗ | H1: Открытые вопросы и примечания
A2: CAT-01 | B2: Вести каталог товаров и услуг | C2: Команда платформы | D2: Хранит товары или услуги бизнеса, которые можно заказать или забронировать. | E2: Каналы бизнеса показывают актуальный каталог. | F2: ТР-6.1 | G2: Утверждено | H2: Настройка — разработчики при внедрении (ТР-8.8).
A3: CAT-02 | B3: Выбрать товар или услугу при оформлении | C3: Клиент бизнеса | D3: Даёт привязать к обращению позиции каталога. | E3: Заказ или бронирование содержит выбранные позиции. | F3: ТР-4.1; ТР-6.1 | G3: Утверждено

Sheet Платежи
A1: ID | B1: Use case | C1: Актор | D1: Что делает система | E1: Результат | F1: Требования ТЗ | G1: Статус в ТЗ | H1: Открытые вопросы и примечания
A2: PAY-01 | B2: Получить данные об оплате от сайта | C2: Клиентская система | D2: Сайт бизнеса сообщает об оплате, принятой на нём. Повторное сообщение об одной оплате не учитывается дважды. | E2: Оплата учтена в статистике дохода. | F2: ТР-9.2; ТР-7.2 | G2: Утверждено | H2: Деньги через систему не проходят (ТР-9.1).
A3: PAY-02 | B3: Получить данные об оплатах из банка | C3: Банк бизнеса | D3: Забирает сведения об операциях из банка владельца бизнеса. | E3: Оплаты учтены без участия сайта и владельца. | F3: ТР-9.2 | G3: Не определено | H3: ОВ-11. Не на старте: банки подключаются по одному.
A4: PAY-03 | B4: Отметить оплату вручную | C4: Бизнес | D4: Даёт отметить оплату по делу вручную, например за наличные. | E4: Оплата учтена без провайдера. | F4: ТР-9.1; ТР-9.2 | G4: Утверждено
A5: PAY-04 | B5: Узнать статус оплаты дела | C5: Бизнес | D5: Показывает факт и статус оплаты по конкретному делу. | E5: Видно, оплачено ли дело. | F5: ТР-6.1 | G5: Утверждено | H5: Модуль платежей необязателен: барбершоп и дизайнер могут работать без него.

Sheet Уведомления
A1: ID | B1: Use case | C1: Актор | D1: Что делает система | E1: Результат | F1: Требования ТЗ | G1: Статус в ТЗ | H1: Открытые вопросы и примечания
A2: NOT-01 | B2: Уведомить клиента о приёме обращения | C2: Система (автоматически) | D2: Сообщает клиенту, что обращение принято. | E2: Клиент знает, что обращение получено. | F2: ТР-10.1; ТР-10.2 | G2: Утверждено | H2: Каналы: email и/или Telegram, хотя бы один.
A3: NOT-02 | B3: Уведомить клиента о смене статуса | C3: Система (автоматически) | D3: Сообщает клиенту об изменении состояния его обращения. | E3: Клиент в курсе хода обращения. | F3: ТР-10.1; ТР-10.2 | G3: Утверждено
A4: NOT-03 | B4: Уведомить бизнес о новом обращении | C4: Система (автоматически) | D4: Сообщает бизнесу о поступлении нового обращения. | E4: Бизнес быстро реагирует на обращение. | F4: ТР-10.1; ТР-10.2 | G4: Утверждено
A5: NOT-04 | B5: Настроить тексты сообщений клиенту | C5: Бизнес | D5: Даёт владельцу самому задать тексты сообщений клиенту; рассылку выполняет система. | E5: Клиент получает сообщения в стиле бизнеса. | F5: ТР-10.3 | G5: Утверждено | H5: Канал «на телефон» — ОВ-13.
A6: NOT-05 | B6: Напомнить владельцу о записи | C6: Система (автоматически) | D6: Напоминает владельцу о предстоящих записях. | E6: Владелец не пропускает клиентов. | F6: ТР-10.4 | G6: Утверждено
A7: NOT-06 | B7: Гарантированно доставить событие | C7: Система (автоматически) | D7: Если получатель (канал доставки или клиентская система) временно недоступен, событие не теряется и доставляется позже. | E7: Ни одно уведомление не потеряно. | F7: ТР-14.4; ТР-13.1; ADR-0003 | G7: Утверждено | H7: Через outbox и RabbitMQ. SMS и push отложены (ТР-10.1).

Sheet Интерфейс владельца
A1: ID | B1: Use case | C1: Актор | D1: Что делает система | E1: Результат | F1: Требования ТЗ | G1: Статус в ТЗ | H1: Открытые вопросы и примечания
A2: OWN-01 | B2: Войти из админ-панели сайта | C2: Бизнес | D2: Открывает CRM по одноразовой подписанной ссылке, которую сервер сайта запрашивает у системы. Отдельного логина нет. | E2: Владелец или сотрудник в CRM своего бизнеса. | F2: ТР-11.4; ADR-0005 | G2: Утверждено | H2: У бизнеса может быть несколько пользователей; каждый видит только свой бизнес.
A3: OWN-02 | B3: Вести доску обращений | C3: Бизнес | D3: Показывает обращения по колонкам состояний; состояние меняется переносом или отметкой («опоздал», «не пришёл»). | E3: Актуальная картина дня. | F3: ТР-11.5; ТР-6.1 | G3: Утверждено | H3: Колонки задаются типом дела.
A4: OWN-03 | B4: Создать запись вручную | C4: Бизнес | D4: Создаёт обращение и клиента вручную — запись по телефону или клиент без записи. | E4: Все клиенты в системе, даже пришедшие напрямую. | F4: ТР-11.6 | G4: Утверждено
A5: OWN-04 | B5: Работать с ПК и телефона одновременно | C5: Бизнес | D5: Изменение на одном устройстве появляется на остальных без перезагрузки. | E5: Барбер отмечает клиента с телефона, на ПК видно сразу. | F5: ТР-11.7 | G5: Утверждено
A6: OWN-05 | B6: Записать на время без накладок | C6: Бизнес | D6: Хранит длительность записи и не даёт поставить две записи одному исполнителю на одно время. | E6: Нет двойных записей. | F6: ТР-11.8 | G6: Утверждено
A7: OWN-06 | B7: Посмотреть доход и итоги дня | C7: Бизнес | D7: Считает доход за день и месяц по данным об оплатах, условный налог по проценту владельца, итоги дня. | E7: Владелец видит выручку и закрывает день. | F7: ТР-11.9 | G7: Утверждено | H7: Налог — справочный расчёт, не касса.
A8: OWN-07 | B8: Посмотреть новых клиентов | C8: Бизнес | D8: Считает клиентов, впервые обратившихся к бизнесу. | E8: Видно, сколько клиентов приносит сайт. | F8: ТР-8.7; ТР-11.9 | G8: Утверждено | H8: Сотрудники бизнеса не учитываются.
A9: OWN-08 | B9: Составить свой отчёт | C9: Бизнес | D9: Даёт собрать отчёт из доступных показателей. | E9: Статистика под нужды конкретного бизнеса. | F9: ТР-11.10 | G9: Утверждено
A10: OWN-09 | B10: Работать в мобильном приложении | C10: Бизнес | D10: Даёт те же возможности, что веб-дашборд, в приложении на телефоне. | E10: Владелец работает без ПК. | F10: ТР-12.2; ТР-12.4; ADR-0006 | G10: Утверждено | H10: Платформы (Android / iOS) — ОВ-15.

Sheet Каналы
A1: ID | B1: Use case | C1: Актор | D1: Что делает система | E1: Результат | F1: Требования ТЗ | G1: Статус в ТЗ | H1: Открытые вопросы и примечания
A2: CH-01 | B2: Подключить существующий сайт | C2: Команда платформы | D2: Подключает работающий сайт бизнеса с минимальными правками его кода: создание обращений и получение статусов. | E2: Сайт передаёт обращения в систему. | F2: ТР-4.2; ТР-8.1 | G2: Утверждено | H2: Совсем без правок кода подключить нельзя. Доступ к коду каждого сайта — ОВ-8.
A3: CH-02 | B3: Подключить сайт на любом стеке | C3: Команда платформы | D3: Подключает сайт на PHP, C# или другом стеке только через HTTP-контракт, без библиотек под язык сайта. | E3: Любой сайт бизнеса может работать с CRM. | F3: ТР-8.4; ТР-8.8; ADR-0004 | G3: Утверждено | H3: Подключение и настройку делают разработчики.
A4: CH-03 | B4: Принимать обращения через Telegram-бота | C4: Клиент бизнеса | D4: Бот от имени бизнеса заводит клиента и обращение, как обычный канал. | E4: Клиент оформляет обращение прямо в Telegram. | F4: ТР-4.2; ТР-8.2 | G4: Утверждено
A5: CH-04 | B5: Подключить новый сайт по контракту | C5: Команда платформы | D5: Новый сайт работает с системой по опубликованному, версионированному контракту. | E5: Новый сайт подключается без доработки ядра. | F5: ТР-4.2; ТР-8.3; ТР-5.3 | G5: Утверждено
A6: CH-05 | B6: Вести обращения с телефона | C6: Бизнес | D6: Даёт владельцу бизнеса с телефона видеть и вести обращения так же, как с ПК. | E6: Владелец работает с заявками без ПК. | F6: ТР-12.1; ТР-12.2; ТР-4.4 | G6: Утверждено | H6: Способ входа владельца в систему не определён (issue #8).

Sheet Эксплуатация
A1: ID | B1: Use case | C1: Актор | D1: Что делает система | E1: Результат | F1: Требования ТЗ | G1: Статус в ТЗ | H1: Открытые вопросы и примечания
A2: OPS-01 | B2: Проверить работоспособность | C2: Команда платформы | D2: Отвечает на внешнюю проверку «живо ли». Упавший сервис перезапускается автоматически. | E2: Сбой обнаруживается и устраняется без ручного вмешательства. | F2: ТР-14.1 | G2: Утверждено
A3: OPS-02 | B3: Сделать резервную копию и восстановиться | C3: Команда платформы | D3: Регулярно сохраняет копию данных. Восстановление из копии проверяется. | E3: Данные не теряются при аварии. | F3: ТР-14.2 | G3: Утверждено | H3: Цель — сохранность данных и восстановление, а не безотказность.
A4: OPS-03 | B4: Оповестить команду об отказе | C4: Система (автоматически) | D4: Ведёт журнал работы и сообщает команде о сбоях раньше, чем пожалуется клиент. | E4: Команда узнаёт о проблеме первой. | F4: ТР-14.5 | G4: Утверждено

Sheet Бизнес-кейсы
A1: Бизнес-кейс | B1: Основной сценарий | C1: Каталог | D1: Оплата | E1: Задействованные use case | F1: Примечание
A2: Барбершоп | B2: Запись на определённое время | C2: Нет | D2: Необязательна | E2: CASE-01, CLI-01, NOT-01…03 | F2: Вторая вертикаль для проверки универсальности (ТР-4.3, на согласовании)
A3: Дизайнер интерьеров | B3: Заявка на консультацию | C3: Нет | D3: Необязательна | E3: CASE-01, CLI-01, NOT-01…03
A4: Туристический сайт | B4: Бронирование с оплатой | C4: Да | D4: Да | E4: CASE-01, CAT-01, CAT-02, PAY-01…03, NOT-01…03
A5: Маркетплейс изделий | B5: Заказ товара с оплатой | C5: Да | D5: Да | E5: CASE-01, CAT-01, CAT-02, PAY-01…03, NOT-01…03 | F5: Первая вертикаль (ТР-4.3, ТР-7.2)
A7: Источник: ТР-4.1, ТР-6.1 (Payment — опциональный модуль, Product/Service — только для кейсов с каталогом).

Sheet Акторы
A1: Актор | B1: Кто это
A2: Клиент бизнеса | B2: Физлицо, потребитель услуг бизнеса. Доступа к CRM не имеет: оформляет обращения через сайт бизнеса или Telegram-бот (ТР-4.4).
A3: Бизнес | B3: Владелец подключённого бизнеса — единственный, кто работает с CRM напрямую (веб и мобильный интерфейс).
A4: Команда платформы | B4: Разработчики OmniaCRM: подключают и настраивают бизнесы и их сайты (ТР-8.8), следят за работой системы.
A5: Клиентская система | B5: Сайт, Telegram-бот или мобильный интерфейс, через который клиент обращается к системе.
A6: Банк бизнеса | B6: Банк владельца бизнеса, из которого система получает сведения об оплатах (ОВ-11).
A7: Система (автоматически) | B7: Действия, которые система выполняет сама, без участия человека.
